tests/__init__.py
tests/tests.py
vec2best/__init__.py
vec2best/functions.py
vec2best/more_sim_benchmarks.py
vec2best/8-8-8/scorer_outlierdetection.py
vec2best/8-8-8/8-8-8_Dataset/Apostles_of_Jesus_Christ.txt
vec2best/8-8-8/8-8-8_Dataset/Big_cats.txt
vec2best/8-8-8/8-8-8_Dataset/European_football_teams.txt
vec2best/8-8-8/8-8-8_Dataset/German_car_manufacturers.txt
vec2best/8-8-8/8-8-8_Dataset/Information_Technology_companies.txt
vec2best/8-8-8/8-8-8_Dataset/Months.txt
vec2best/8-8-8/8-8-8_Dataset/Solar_System_planets.txt
vec2best/8-8-8/8-8-8_Dataset/SouthAmerica.txt
vec2best/wiki-sem-500/README.md
vec2best/wiki-sem-500/evaluate.py
vec2best/wiki-sem-500/install_dependencies.py
vec2best/wiki-sem-500/run_tests.py
vec2best/wiki-sem-500/src/__init__.py
vec2best/wiki-sem-500/src/embeddings.py
vec2best/wiki-sem-500/src/evaluator.py
vec2best/wiki-sem-500/src/outlier_test_group.py
vec2best/wiki-sem-500/src/utils.py
vec2best/wiki-sem-500/src/lib/polyglot/__init__.py
vec2best/wiki-sem-500/src/lib/polyglot/base.py
vec2best/wiki-sem-500/src/lib/polyglot/utils.py
vec2best/wiki-sem-500/src/lib/polyglot/mapping/__init__.py
vec2best/wiki-sem-500/src/lib/polyglot/mapping/base.py
vec2best/wiki-sem-500/src/lib/polyglot/mapping/embeddings.py
vec2best/wiki-sem-500/src/lib/polyglot/mapping/expansion.py
vec2best/wiki-sem-500/wiki-sem-500/en/Q101352.txt
vec2best/wiki-sem-500/wiki-sem-500/en/Q10417670.txt
vec2best/wiki-sem-500/wiki-sem-500/en/Q105000.txt
vec2best/wiki-sem-500/wiki-sem-500/en/Q1060829.txt
vec2best/wiki-sem-500/wiki-sem-500/en/Q1061151.txt
vec2best/wiki-sem-500/wiki-sem-500/en/Q106658.txt
vec2best/wiki-sem-500/wiki-sem-500/en/Q1066984.txt
vec2best/wiki-sem-500/wiki-sem-500/en/Q1068842.txt
vec2best/wiki-sem-500/wiki-sem-500/en/Q10689397.txt
vec2best/wiki-sem-500/wiki-sem-500/en/Q1070990.txt
vec2best/wiki-sem-500/wiki-sem-500/en/Q10742.txt
vec2best/wiki-sem-500/wiki-sem-500/en/Q10843872.txt
vec2best/wiki-sem-500/wiki-sem-500/en/Q1093829.txt
vec2best-1.1.0.dist-info/METADATA
vec2best-1.1.0.dist-info/WHEEL
vec2best-1.1.0.dist-info/top_level.txt
vec2best-1.1.0.dist-info/RECORD
