Metadata-Version: 2.1
Name: vec2best
Version: 1.1.0
Summary: A Unified Framework for Intrinsic Evaluation of Word-Embedding Algorithms
Home-page: UNKNOWN
Author: Anna Giabelli
Author-email: anna.giabelli@unimib.it
License: UNKNOWN
Platform: UNKNOWN
Classifier: Intended Audience :: Developers
Classifier: Programming Language :: Python :: 3.6
Classifier: Operating System :: OS Independent
Requires-Dist: six
Requires-Dist: scikit-learn (==0.22.1)
Requires-Dist: word-embeddings-benchmarks (==0.0.1)
